varya/__init__.py
varya/compose/__compose.py
varya/compose/__init__.py
varya/compose/core.py
varya/metrics/__init__.py
varya/metrics/classification.py
varya/metrics/regression.py
varya/model_selection/__init__.py
varya/model_selection/_split.py
varya/preprocessing/__init__.py
varya/preprocessing/_split.py
varya/utils/__init__.py
varya/utils/distances.py
varya/utils/probe.py
varya/utils/recast.py
varya/utils/tools.py
varya/utils/validation.py
varya/utils/verify.py
varya/utlis/__init__.py
varya/utlis/validation.py
varya-0.1.0.dist-info/LICENSE
varya-0.1.0.dist-info/METADATA
varya-0.1.0.dist-info/WHEEL
varya-0.1.0.dist-info/top_level.txt
varya-0.1.0.dist-info/RECORD
